[
  {
    "additions": 15,
    "author": {
      "id": "MDQ6VXNlcjE2OTIwMDk=",
      "is_bot": false,
      "login": "simonbyrne",
      "name": "Simon Byrne"
    },
    "body": "Needed to register the package: https://github.com/JuliaRegistries/General/pull/47050#issuecomment-947129094",
    "changedFiles": 2,
    "closingIssuesReferences": [],
    "createdAt": "2021-10-19T21:55:32Z",
    "deletions": 0,
    "labels": [
      {
        "color": "6886BC",
        "description": "",
        "id": "LA_kwDOFT2Pms7Our0a",
        "name": "ClimaCoreVTK"
      }
    ],
    "mergedAt": "2021-10-20T00:45:31Z",
    "number": 261,
    "title": "[VTK] add compat bounds and license"
  },
  {
    "additions": 58,
    "author": {
      "id": "MDQ6VXNlcjE2OTIwMDk=",
      "is_bot": false,
      "login": "simonbyrne",
      "name": "Simon Byrne"
    },
    "body": "This should fix the even-numbered element issue from #255.",
    "changedFiles": 2,
    "closingIssuesReferences": [],
    "createdAt": "2021-10-20T20:39:02Z",
    "deletions": 52,
    "labels": [],
    "mergedAt": "2021-10-20T23:19:37Z",
    "number": 262,
    "title": "Define UV at the pole to be consistent with long=0"
  }
]