[
  {
    "additions": 40,
    "author": {
      "id": "MDQ6VXNlcjE2OTIwMDk=",
      "is_bot": false,
      "login": "simonbyrne",
      "name": "Simon Byrne"
    },
    "body": "Adds a new GitHub workflow that checks for invalidations when loading\r\n\r\n- [x] Code follows the [style guidelines](https://clima.github.io/ClimateMachine.jl/latest/DevDocs/CodeStyle/) OR N/A.\r\n- [x] Unit tests are included OR N/A.\r\n- [x] Code is exercised in an integration test OR N/A.\r\n- [x] Documentation has been added/updated OR N/A.\r\n",
    "changedFiles": 1,
    "closingIssuesReferences": [],
    "createdAt": "2022-09-29T18:27:49Z",
    "deletions": 0,
    "labels": [],
    "mergedAt": "2022-10-04T19:26:49Z",
    "number": 972,
    "title": "add invalidations test"
  },
  {
    "additions": 556,
    "author": {
      "id": "MDQ6VXNlcjE4ODA2NDE=",
      "is_bot": false,
      "login": "charleskawczynski",
      "name": "Charles Kawczynski"
    },
    "body": "This PR extends and fixes `Ref` broadcasting with StencilCoefs (#963), solution was basically the same as the one applied in #945. Closes #963.\r\n\r\nI tried applying only `copyto!`, and only `apply_stencil!`, but that didn't work so I applied to all three methods (which does work).",
    "changedFiles": 8,
    "closingIssuesReferences": [
      {
        "id": "I_kwDOFT2Pms5SqYrs",
        "number": 963,
        "repository": {
          "id": "MDEwOlJlcG9zaXRvcnkzNTYzNTU5OTQ=",
          "name": "ClimaCore.jl",
          "owner": {
            "id": "MDEyOk9yZ2FuaXphdGlvbjQzMTYxMTg4",
            "login": "CliMA"
          }
        },
        "url": "https://github.com/CliMA/ClimaCore.jl/issues/963"
      }
    ],
    "createdAt": "2022-10-02T22:40:03Z",
    "deletions": 497,
    "labels": [
      {
        "color": "E31312",
        "description": "",
        "id": "MDU6TGFiZWwzMjgwMjU1MzY4",
        "name": "performance"
      }
    ],
    "mergedAt": "2022-10-04T20:16:59Z",
    "number": 978,
    "title": "Extend and fix Ref broadcasting with StencilCoefs"
  }
]