[
  {
    "additions": 4,
    "author": {
      "id": "MDQ6VXNlcjE4ODA2NDE=",
      "is_bot": false,
      "login": "charleskawczynski",
      "name": "Charles Kawczynski"
    },
    "body": "This PR updates the readme for a PR since the last release.",
    "changedFiles": 1,
    "closingIssuesReferences": [],
    "createdAt": "2024-02-29T17:58:15Z",
    "deletions": 0,
    "labels": [],
    "mergedAt": "2024-02-29T18:11:56Z",
    "number": 1633,
    "title": "Update news from previous PR"
  }
]