[
  {
    "additions": 81,
    "author": {
      "id": "MDQ6VXNlcjE4ODA2NDE=",
      "is_bot": false,
      "login": "charleskawczynski",
      "name": "Charles Kawczynski"
    },
    "body": "This PR bumps the patch version for a new release of ClimaCore.",
    "changedFiles": 5,
    "closingIssuesReferences": [],
    "createdAt": "2025-01-27T22:59:41Z",
    "deletions": 77,
    "labels": [
      {
        "color": "93013E",
        "description": "",
        "id": "LA_kwDOFT2Pms73S5e5",
        "name": "Release"
      },
      {
        "color": "06CF1E",
        "description": "",
        "id": "LA_kwDOFT2Pms8AAAABAlTlKw",
        "name": "Dependencies"
      }
    ],
    "mergedAt": "2025-01-28T00:38:26Z",
    "number": 2164,
    "title": "Bump patch version, update dependencies"
  },
  {
    "additions": 120,
    "author": {
      "id": "MDQ6VXNlcjg4NTUyNTg=",
      "is_bot": false,
      "login": "dennisYatunin",
      "name": "Dennis Yatunin"
    },
    "body": "<!-- Provide a clear description of the content -->\r\n~This PR extends the DSS machinery to handle 3D weights alongside 2D weights, and it fixes the weights for deep-atmosphere grids. The weights are now always consistent with the metric determinant $J$, ensuring that DSS does not violate conservation of scalars or vorticity in ClimaAtmos.~ **Update:** This turned out not to be necessary (see comment below).\r\n\r\nIn addition, this PR adds a unit test for conservation and enforces consistency of function/variable names, ensuring that the weights are always called `dss_weights` and updating docstrings where needed. It also fixes a preexisting bug in DSS buffer allocation for, e.g., `Covariant12Vector`s, which are transformed into `UVWVector`s when DSSed in a 3D space, and so have `Nf = 2` for the input data and `Nf = 3` for the buffer. There was previously a line in the Topologies module that assumed these values of `Nf` are equal.\r\n\r\n- [x] Code follows the [style guidelines](https://clima.github.io/ClimateMachine.jl/latest/DevDocs/CodeStyle/) OR N/A.\r\n- [x] Unit tests are included OR N/A.\r\n- [x] Code is exercised in an integration test OR N/A.\r\n- [x] Documentation has been added/updated OR N/A.\r\n",
    "changedFiles": 15,
    "closingIssuesReferences": [],
    "createdAt": "2025-01-17T01:08:42Z",
    "deletions": 99,
    "labels": [
      {
        "color": "52C059",
        "description": "",
        "id": "LA_kwDOFT2Pms7eKbJ1",
        "name": "bugfix"
      }
    ],
    "mergedAt": "2025-01-28T00:59:40Z",
    "number": 2136,
    "title": " Clarify DSS weights and fix DSS buffer bug"
  }
]