[
  {
    "additions": 4,
    "author": {
      "id": "MDQ6VXNlcjYwMDQ5ODM3",
      "is_bot": false,
      "login": "nefrathenrici",
      "name": "Nat Efrat-Henrici"
    },
    "body": "Updating to v1! I believe the only breaking change is the removal of `AbstractTOMLDict`.",
    "changedFiles": 3,
    "closingIssuesReferences": [],
    "createdAt": "2025-09-05T18:34:51Z",
    "deletions": 4,
    "labels": [],
    "mergedAt": "2025-09-09T16:25:50Z",
    "number": 280,
    "title": "Update ClimaParams"
  }
]