[
  {
    "additions": 1378,
    "author": {
      "id": "MDQ6VXNlcjE1MTg1MzE2",
      "is_bot": false,
      "login": "tapios",
      "name": "Tapio Schneider"
    },
    "body": "Documentation:\r\n- New README (badges, quick start, features, design principles) and logo\r\n- Restructure docs into getting-started, how-to, and design-philosophy pages\r\n- Revise docstrings throughout to follow CliMA documentation policy\r\n- Correct stale docs (MPI auto-detection was removed; FileLogger export)\r\n\r\nBug fixes (with regression tests):\r\n- Add missing abort method for SingletonCommsContext\r\n- Base.summary(io, device) now prints to io per the Base contract\r\n- FileLogger no longer crashes when an MPI run reuses a log_dir\r\n- Invalid coarsen option throws ArgumentError instead of StackOverflowError\r\n- Singleton reduce/allreduce/gather return copies, matching MPI methods\r\n\r\nCompat/CI:\r\n- Raise minimum Julia to 1.10 (LTS) and test 1.10 - 1.12 in CI\r\n\r\nCloses #92, #88, #107 ",
    "changedFiles": 26,
    "closingIssuesReferences": [
      {
        "id": "I_kwDOGUSWBM6UcMsV",
        "number": 92,
        "repository": {
          "id": "R_kgDOGUSWBA",
          "name": "ClimaComms.jl",
          "owner": {
            "id": "MDEyOk9yZ2FuaXphdGlvbjQzMTYxMTg4",
            "login": "CliMA"
          }
        },
        "url": "https://github.com/CliMA/ClimaComms.jl/issues/92"
      }
    ],
    "createdAt": "2026-07-11T23:59:08Z",
    "deletions": 456,
    "labels": [],
    "mergedAt": "2026-07-13T20:59:32Z",
    "number": 149,
    "title": "Update documentation and fix bugs found during audit"
  }
]