[
  {
    "additions": 388,
    "author": {
      "id": "U_kgDOBdh4bA",
      "is_bot": false,
      "login": "ph-kev",
      "name": "Kevin Phan "
    },
    "body": "Masking was typically done with a `OutputVar` whose data consists of `NaN`s and ones. As a result, this led to the `NaN`s poisoning the computations near the coastlines. To remedy this, we add `generate_lonlat_mask` which only uses a `OutputVar` whose data is zeros and ones to determine the mask. Furthermore, this also improves the memory footprint of the mask whose data can now be stored as booleans. Finally, all masking relating functions are moved to `masks.jl`  to help debloat `Var.jl`.\r\n",
    "changedFiles": 9,
    "closingIssuesReferences": [],
    "createdAt": "2025-06-09T23:07:39Z",
    "deletions": 216,
    "labels": [],
    "mergedAt": "2025-06-23T15:40:53Z",
    "number": 287,
    "title": "Add Var.generate_lonlat_mask"
  }
]