[
  {
    "additions": 212,
    "author": {
      "id": "U_kgDOBdh4bA",
      "is_bot": false,
      "login": "ph-kev",
      "name": "Kevin Phan "
    },
    "body": "This PR introduces `transform_dates!` and `set_reference_date!`. The first function is an in-place version of `transform_dates`. The second function updates the reference/start date and the time dimension of a `OutputVar`.\r\n\r\nAdding both of these functions allow for the deprecation of `new_start_date` and `shift_by` which remove the responsibility of fixing the dates and times from the `OutputVar` constructor. ",
    "changedFiles": 6,
    "closingIssuesReferences": [],
    "createdAt": "2026-03-06T22:46:26Z",
    "deletions": 6,
    "labels": [],
    "mergedAt": "2026-03-11T23:43:37Z",
    "number": 383,
    "title": "Add utilities for transforming dates in OutputVar"
  }
]