[
  {
    "additions": 407,
    "author": {
      "id": "MDQ6VXNlcjUxMzk3MTg2",
      "is_bot": false,
      "login": "juliasloan25",
      "name": "Julia Sloan"
    },
    "body": "<!--- THESE LINES ARE COMMENTED -->\r\n## Purpose \r\nUpdate dependencies for recent minor releases of CliMA packages:\r\n```\r\n    Updating `~/clima/ClimaLand.jl/.buildkite/Project.toml`\r\n  [052768ef] \u2191 CUDA v5.8.2 \u21d2 v5.8.3\r\n  [d414da3d] \u2191 ClimaCore v0.14.38 \u21d2 v0.14.39\r\n  [08f4d4ce] ~ ClimaLand v0.18.2 `..` \u21d2 v0.19.0 `..`\r\n  [5c42b081] \u2191 ClimaParams v0.11.1 \u21d2 v0.12.1\r\n  [a93c6f00] \u2191 DataFrames v1.7.0 \u21d2 v1.7.1\r\n  [e98cc03f] \u2191 Insolation v0.9.5 \u21d2 v0.10.1\r\n  [49b00bb7] \u2191 SurfaceFluxes v0.12.1 \u21d2 v0.12.2\r\n  [b60c26fb] \u2191 Thermodynamics v0.13.1 \u21d2 v0.14.0\r\n```\r\n\r\nAlso makes a minor release because of recent breaking changes in ClimaLand - see NEWS.md for details.\r\n\r\nCloses #1365, #1364, and #1357\r\n\r\n## Note\r\n\r\nThe docbuild was failing because the output from the global snowy_land.jl tutorial was too large (even with semicolons suppressing output). See the error below. To fix this I lowered the resolution of that run and added a note about it.\r\n<img width=\"811\" height=\"168\" alt=\"Screenshot 2025-08-27 at 12 21 20\u202fPM\" src=\"https://github.com/user-attachments/assets/feecbb4d-eadc-4fca-a5c5-5070d899b1ef\" />\r\n\r\nThere were also warnings about the output size for 2 other docs pages, so I minimized those as well (APIs/shared_utilities.md, standalone/Soil/evaporation.md).\r\n",
    "changedFiles": 17,
    "closingIssuesReferences": [],
    "createdAt": "2025-08-26T10:34:31Z",
    "deletions": 355,
    "labels": [],
    "mergedAt": "2025-08-28T15:25:32Z",
    "number": 1375,
    "title": "tag v0.19.0; up deps"
  },
  {
    "additions": 103,
    "author": {
      "id": "MDQ6VXNlcjY1OTc5MjA1",
      "is_bot": false,
      "login": "kmdeck",
      "name": ""
    },
    "body": "<!--- THESE LINES ARE COMMENTED -->\r\n## Purpose \r\nAdds model callbacks by default to the simulation struct; makes it so the user does not need to create/know about the pmodel callback themselves\r\n\r\n\r\n## To-do\r\n\r\n\r\n## Content\r\n<!---  specific tasks that are currently complete \r\n- Solution implemented\r\n-->\r\n\r\n\r\n<!---\r\nReview checklist\r\n\r\nI have:\r\n- followed the codebase contribution guide: https://clima.github.io/ClimateMachine.jl/latest/Contributing/\r\n- followed the style guide: https://clima.github.io/ClimateMachine.jl/latest/DevDocs/CodeStyle/\r\n- followed the documentation policy: https://github.com/CliMA/policies/wiki/Documentation-Policy\r\n- checked that this PR does not duplicate an open PR.\r\n\r\nIn the Content, I have included \r\n- relevant unit tests, and integration tests, \r\n- appropriate docstrings on all functions, structs, and modules, and included relevant documentation.\r\n\r\n-->\r\n\r\n----\r\n- [ ] I have read and checked the items on the review checklist.\r\n",
    "changedFiles": 11,
    "closingIssuesReferences": [],
    "createdAt": "2025-08-27T00:32:18Z",
    "deletions": 32,
    "labels": [],
    "mergedAt": "2025-08-28T19:04:58Z",
    "number": 1381,
    "title": "add model callbacks"
  },
  {
    "additions": 192,
    "author": {
      "id": "MDQ6VXNlcjY1OTc5MjA1",
      "is_bot": false,
      "login": "kmdeck",
      "name": ""
    },
    "body": "<!--- THESE LINES ARE COMMENTED -->\r\n## Purpose \r\nFor clarity, move LAI to the Canopy section of the code, and let \"drivers\" refer only to external forcing.\r\n\r\n\r\n## To-do\r\n<!---  list of proposed tasks in the PR, move to \"Content\" on completion \r\n- Proposed task\r\n-->\r\n\r\n\r\n## Content\r\n<!---  specific tasks that are currently complete \r\n- Solution implemented\r\n-->\r\n\r\n\r\n<!---\r\nReview checklist\r\n\r\nI have:\r\n- followed the codebase contribution guide: https://clima.github.io/ClimateMachine.jl/latest/Contributing/\r\n- followed the style guide: https://clima.github.io/ClimateMachine.jl/latest/DevDocs/CodeStyle/\r\n- followed the documentation policy: https://github.com/CliMA/policies/wiki/Documentation-Policy\r\n- checked that this PR does not duplicate an open PR.\r\n\r\nIn the Content, I have included \r\n- relevant unit tests, and integration tests, \r\n- appropriate docstrings on all functions, structs, and modules, and included relevant documentation.\r\n\r\n-->\r\n\r\n----\r\n- [ ] I have read and checked the items on the review checklist.\r\n",
    "changedFiles": 26,
    "closingIssuesReferences": [],
    "createdAt": "2025-08-28T17:02:30Z",
    "deletions": 125,
    "labels": [
      {
        "color": "D93F0B",
        "description": "",
        "id": "LA_kwDOGiZe4s8AAAABfro14Q",
        "name": "breaking change"
      }
    ],
    "mergedAt": "2025-08-28T19:14:54Z",
    "number": 1386,
    "title": "move LAI to canopy directory"
  },
  {
    "additions": 387,
    "author": {
      "id": "MDQ6VXNlcjIyMTYwMjU3",
      "is_bot": false,
      "login": "AlexisRenchon",
      "name": "Alexandre Alexis Renchon"
    },
    "body": "closes #1346\r\n\r\npreview: https://clima.github.io/ClimaLand.jl/previews/PR1367/\r\n\r\nNote: before merging, need to checkout docs/make.jl\r\n\r\nOnly the structs themselves show up in the API docs, not the constructor functions.\r\nThis commit fixes this issue.",
    "changedFiles": 15,
    "closingIssuesReferences": [
      {
        "id": "I_kwDOGiZe4s7GyZjV",
        "number": 1346,
        "repository": {
          "id": "R_kgDOGiZe4g",
          "name": "ClimaLand.jl",
          "owner": {
            "id": "MDEyOk9yZ2FuaXphdGlvbjQzMTYxMTg4",
            "login": "CliMA"
          }
        },
        "url": "https://github.com/CliMA/ClimaLand.jl/issues/1346"
      }
    ],
    "createdAt": "2025-08-22T19:31:49Z",
    "deletions": 13,
    "labels": [],
    "mergedAt": "2025-08-28T19:36:19Z",
    "number": 1367,
    "title": "Add constructors API"
  }
]