[
  {
    "additions": 24,
    "author": {
      "id": "MDQ6VXNlcjUxMzk3MTg2",
      "is_bot": false,
      "login": "juliasloan25",
      "name": "Julia Sloan"
    },
    "body": "<!--- THESE LINES ARE COMMENTED -->\r\n## Purpose \r\nChange the physics of the OceananigansSimulation model, per Simone's suggestions. This is more similar to the model setup in the ClimaOcean [one degree example](https://clima.github.io/ClimaOceanDocumentation/stable/literated/one_degree_simulation/), but not exactly the same.\r\n\r\nTaken from #1501 to make that PR smaller.\r\nThis may be behavior changing for CMIP, but I don't see any changes visually in the buildkite plots.",
    "changedFiles": 3,
    "closingIssuesReferences": [],
    "createdAt": "2025-10-22T00:57:24Z",
    "deletions": 6,
    "labels": [],
    "mergedAt": "2025-10-23T20:07:11Z",
    "number": 1524,
    "title": "change Oceananigans model closures"
  },
  {
    "additions": 242,
    "author": {
      "id": "MDQ6VXNlcjUxMzk3MTg2",
      "is_bot": false,
      "login": "juliasloan25",
      "name": "Julia Sloan"
    },
    "body": "<!--- THESE LINES ARE COMMENTED -->\r\n## Purpose \r\nProvide downward shortwave and longwave radiative fluxes to surface models, instead of using F_radiative.\r\n\r\nAfter some upstream changes the downgrade test is failing due to StaticArrays, so I bumped the compat.\r\n\r\n## To-do\r\n- [x] don't get F_radiative from the atmosphere\r\n- [x] pass SW_d, LW_d to component models\r\n- [x] use these to compute net radiation correctly\r\n\r\n## To do in future PRs\r\n- [ ] store SW_d, LW_d in bucket cache instead of in BucketSimulation (requires ClimaLand change)\r\n\r\n\r\n<!---\r\nReview checklist\r\n\r\nI have:\r\n- followed the codebase contribution guide: https://clima.github.io/ClimateMachine.jl/latest/Contributing/\r\n- followed the style guide: https://clima.github.io/ClimateMachine.jl/latest/DevDocs/CodeStyle/\r\n- followed the documentation policy: https://github.com/CliMA/policies/wiki/Documentation-Policy\r\n- checked that this PR does not duplicate an open PR.\r\n\r\nIn the Content, I have included \r\n- relevant unit tests, and integration tests, \r\n- appropriate docstrings on all functions, structs, and modules, and included relevant documentation.\r\n\r\n-->\r\n\r\n----\r\n- [ ] I have read and checked the items on the review checklist.\r\n",
    "changedFiles": 16,
    "closingIssuesReferences": [],
    "createdAt": "2025-10-20T23:11:16Z",
    "deletions": 123,
    "labels": [],
    "mergedAt": "2025-10-23T22:48:15Z",
    "number": 1518,
    "title": "fix radiative flux over surface models"
  }
]