[
  {
    "additions": 323,
    "author": {
      "id": "MDQ6VXNlcjQzNzEwMDQ1",
      "is_bot": false,
      "login": "akshaysridhar",
      "name": "Akshay Sridhar"
    },
    "body": "Solve flux balance at ice-surface to diagnose surface temperature. Passes an `update_T_sfc` callback function to the surface fluxes function (positional argument). \r\n\r\nCloses #1649 \r\n",
    "changedFiles": 4,
    "closingIssuesReferences": [
      {
        "id": "I_kwDOEn8xDc7iJ2Yr",
        "number": 1649,
        "repository": {
          "id": "MDEwOlJlcG9zaXRvcnkzMTAzMjU1MTc=",
          "name": "ClimaCoupler.jl",
          "owner": {
            "id": "MDEyOk9yZ2FuaXphdGlvbjQzMTYxMTg4",
            "login": "CliMA"
          }
        },
        "url": "https://github.com/CliMA/ClimaCoupler.jl/issues/1649"
      }
    ],
    "createdAt": "2026-02-13T23:52:00Z",
    "deletions": 83,
    "labels": [],
    "mergedAt": "2026-03-13T22:53:17Z",
    "number": 1730,
    "title": "Iterative sea ice skin temperature"
  }
]