[
  {
    "additions": 39,
    "author": {
      "id": "U_kgDOBz9FcQ",
      "is_bot": false,
      "login": "amylu00",
      "name": ""
    },
    "body": "added parameters for water based deposition nucleation for kaolinite, feldspar, and ferrihydrate",
    "changedFiles": 2,
    "closingIssuesReferences": [],
    "createdAt": "2024-01-25T22:28:43Z",
    "deletions": 1,
    "labels": [
      {
        "color": "88B2E0",
        "description": "",
        "id": "LA_kwDODuhI_87YQmD9",
        "name": "Microphysics"
      }
    ],
    "mergedAt": "2024-01-25T22:46:40Z",
    "number": 161,
    "title": "ice deposition nucleation parameters"
  }
]