[
  {
    "author": {
      "id": "MDQ6VXNlcjEyNjY0NDQ4",
      "is_bot": false,
      "login": "bischtob",
      "name": "Nawibot"
    },
    "createdAt": "2021-12-30T22:30:48Z",
    "labels": [
      {
        "color": "E45AB5",
        "description": "Issue has high priority",
        "id": "MDU6TGFiZWwzMjc4MDgyNzcx",
        "name": "ASAP"
      }
    ],
    "number": 144,
    "title": "Add nonhydrostatic 3D dry model"
  },
  {
    "author": {
      "id": "MDQ6VXNlcjEyNjY0NDQ4",
      "is_bot": false,
      "login": "bischtob",
      "name": "Nawibot"
    },
    "createdAt": "2021-12-30T22:31:26Z",
    "labels": [
      {
        "color": "E45AB5",
        "description": "Issue has high priority",
        "id": "MDU6TGFiZWwzMjc4MDgyNzcx",
        "name": "ASAP"
      }
    ],
    "number": 145,
    "title": "Add thermodynamics.jl "
  },
  {
    "author": {
      "id": "MDQ6VXNlcjEyNjY0NDQ4",
      "is_bot": false,
      "login": "bischtob",
      "name": "Nawibot"
    },
    "createdAt": "2021-12-30T22:32:12Z",
    "labels": [
      {
        "color": "E45AB5",
        "description": "Issue has high priority",
        "id": "MDU6TGFiZWwzMjc4MDgyNzcx",
        "name": "ASAP"
      }
    ],
    "number": 146,
    "title": "Update ShallowWaterModels.jl"
  },
  {
    "author": {
      "id": "MDQ6VXNlcjEyNjY0NDQ4",
      "is_bot": false,
      "login": "bischtob",
      "name": "Nawibot"
    },
    "createdAt": "2021-12-30T22:32:59Z",
    "labels": [],
    "number": 147,
    "title": "Add Moist Nonhydrostatic 3D model"
  }
]