[
  {
    "additions": 4,
    "author": {
      "id": "MDQ6VXNlcjEzMjA1MTYy",
      "is_bot": false,
      "login": "tomchor",
      "name": "Tom\u00e1s Chor"
    },
    "body": "Changed units for haline contraction coefficients to match what's listed in table 1.2 of Vallis (from ppt to psu).",
    "changedFiles": 2,
    "closingIssuesReferences": [],
    "createdAt": "2021-06-21T17:54:52Z",
    "deletions": 4,
    "labels": [],
    "mergedAt": "2021-06-21T19:46:43Z",
    "number": 1748,
    "title": "Changed units in docstring for linear eq of state"
  },
  {
    "additions": 4,
    "author": {
      "id": "MDQ6VXNlcjEzMjA1MTYy",
      "is_bot": false,
      "login": "tomchor",
      "name": "Tom\u00e1s Chor"
    },
    "body": "I believe there were a couple of typos in the units of the surface heat flux",
    "changedFiles": 1,
    "closingIssuesReferences": [],
    "createdAt": "2021-06-21T17:10:40Z",
    "deletions": 4,
    "labels": [],
    "mergedAt": "2021-06-21T19:49:23Z",
    "number": 1747,
    "title": "Fixed units in ocean wind mixing example"
  }
]