[
  {
    "additions": 10,
    "author": {
      "id": "MDQ6VXNlcjcxMTI3Njg=",
      "is_bot": false,
      "login": "navidcy",
      "name": "Navid C. Constantinou"
    },
    "body": "",
    "changedFiles": 2,
    "closingIssuesReferences": [],
    "createdAt": "2021-11-12T07:00:14Z",
    "deletions": 9,
    "labels": [
      {
        "color": "d2b48c",
        "description": "The sacred scrolls",
        "id": "MDU6TGFiZWwxMjU1NjMxNjM1",
        "name": "documentation \ud83d\udcdc"
      }
    ],
    "mergedAt": "2021-11-13T00:27:53Z",
    "number": 2057,
    "title": "Minor enhancement to ocean mixing example"
  },
  {
    "additions": 49,
    "author": {
      "id": "MDQ6VXNlcjcxMTI3Njg=",
      "is_bot": false,
      "login": "navidcy",
      "name": "Navid C. Constantinou"
    },
    "body": "",
    "changedFiles": 5,
    "closingIssuesReferences": [],
    "createdAt": "2021-11-12T01:24:44Z",
    "deletions": 12,
    "labels": [
      {
        "color": "d2b48c",
        "description": "The sacred scrolls",
        "id": "MDU6TGFiZWwxMjU1NjMxNjM1",
        "name": "documentation \ud83d\udcdc"
      },
      {
        "color": "ffd700",
        "description": "",
        "id": "MDU6TGFiZWwxODc3MDEyNTI0",
        "name": "turbulence closures \ud83c\udf90"
      }
    ],
    "mergedAt": "2021-11-13T10:31:59Z",
    "number": 2056,
    "title": "Add `ConvectiveAdjustmentVerticalDiffusivity` in Docs"
  }
]