[
  {
    "additions": 31,
    "author": {
      "id": "MDQ6VXNlcjMzNTQ3Njk3",
      "is_bot": false,
      "login": "simone-silvestri",
      "name": "Simone Silvestri"
    },
    "body": "see #3141 \r\ncloses #3141 \r\n\r\nThe results from `validation/immersed_boundaries/immersed_couette_flow.jl` from this branch\r\n\r\nhttps://github.com/CliMA/Oceananigans.jl/assets/33547697/e50beac1-4d22-4581-9715-5f541e8dcf01\r\n\r\n",
    "changedFiles": 3,
    "closingIssuesReferences": [
      {
        "id": "I_kwDOCRy_aM5oH6wE",
        "number": 3141,
        "repository": {
          "id": "MDEwOlJlcG9zaXRvcnkxNTI4Nzg5NTI=",
          "name": "Oceananigans.jl",
          "owner": {
            "id": "MDEyOk9yZ2FuaXphdGlvbjQzMTYxMTg4",
            "login": "CliMA"
          }
        },
        "url": "https://github.com/CliMA/Oceananigans.jl/issues/3141"
      }
    ],
    "createdAt": "2023-06-08T15:49:33Z",
    "deletions": 9,
    "labels": [],
    "mergedAt": "2023-07-11T02:06:29Z",
    "number": 3142,
    "title": "(v0.85.0) Switching cells where fluxes are applied in `ImmersedBoundaryCondition` to match `FieldBoundaryConditions`' kwargs"
  }
]