[
  {
    "additions": 1918,
    "author": {
      "id": "MDQ6VXNlcjMzNTQ3Njk3",
      "is_bot": false,
      "login": "simone-silvestri",
      "name": "Simone Silvestri"
    },
    "body": "Yet another optimization for upwind stencil computations.\r\nThe pattern in Oceananigans to perform upwind reconstruction is roughly:\r\n```julia\r\nR_left    = _left_reconstruction(.....)\r\nR_right = _right_reconstruction(.....)\r\n\r\nreturn ifelse(u > 0, u * R_left, u * R_right)\r\n``` \r\n\r\nThis means that we are always performing the reconstruction twice. This is not a huge problem for linear reconstruction schemes (`UpwindBiased`) but leads to register blowup for `WENO` schemes that are extremely heavy to compute. \r\nThis PR aims to push the `left` - `right` choice _inside_ the reconstruction function by realizing that the only difference between left and right reconstruction is how the data is organized in the stencil.\r\nIn this way, only one reconstruction is required significantly reducing register pressure, and consequently, computation time.\r\nThis follows the same pattern found in [SpeedyWeather.jl](https://github.com/SpeedyWeather/SpeedyWeather.jl/blob/4fd8c045fbc493f94b70f121cabf8f8fc3c15f66/src/dynamics/vertical_advection.jl#L124-L148)\r\n\r\nSome benchmarks are implemented in the [NESAPOceananigans.jl](https://github.com/simone-silvestri/NESAPOceananigans.jl) repository. \r\n\r\nHere are some timing tests on main with a **NON-Immersed** grid (launching julia with `julia --project=\"environments/main\" --check-bounds=no`)\r\n```julia \r\njulia> using NESAPOceananigans\r\njulia> set_problem_size!(500, 500, 50)\r\n\r\njulia> trial1 = run_model_benchmark!(momentum_kernel_test, GPU();\r\n                                      use_benchmarktools = true)\r\nBenchmarkTools.Trial: 5 samples with 1 evaluation.\r\n Range (min \u2026 max):  21.916 ms \u2026  22.784 ms  \u250a GC (min \u2026 max): 0.00% \u2026 0.00%\r\n Time  (median):     22.036 ms               \u250a GC (median):    0.00%\r\n Time  (mean \u00b1 \u03c3):   22.144 ms \u00b1 363.318 \u03bcs  \u250a GC (mean \u00b1 \u03c3):  0.00% \u00b1 0.00%\r\n\r\n  \u2588\u2588      \u2588\u2588                                                 \u2588\r\n  \u2588\u2588\u2581\u2581\u2581\u2581\u2581\u2581\u2588\u2588\u2581\u2581\u2581\u2581\u2581\u2581\u2581\u2581\u2581\u2581\u2581\u2581\u2581\u2581\u2581\u2581\u2581\u2581\u2581\u2581\u2581\u2581\u2581\u2581\u2581\u2581\u2581\u2581\u2581\u2581\u2581\u2581\u2581\u2581\u2581\u2581\u2581\u2581\u2581\u2581\u2581\u2581\u2581\u2581\u2581\u2581\u2581\u2581\u2581\u2588 \u2581\r\n  21.9 ms         Histogram: frequency by time         22.8 ms <\r\n\r\n Memory estimate: 245.86 KiB, allocs estimate: 407.\r\n\r\njulia> trial1 = run_model_benchmark!(tracer_kernel_test, GPU();\r\n                                     use_benchmarktools = true)\r\nBenchmarkTools.Trial: 5 samples with 1 evaluation.\r\n Range (min \u2026 max):  14.189 ms \u2026 14.421 ms  \u250a GC (min \u2026 max): 0.00% \u2026 0.00%\r\n Time  (median):     14.261 ms              \u250a GC (median):    0.00%\r\n Time  (mean \u00b1 \u03c3):   14.269 ms \u00b1 93.553 \u03bcs  \u250a GC (mean \u00b1 \u03c3):  0.00% \u00b1 0.00%\r\n\r\n  \u2588\u2588                \u2588   \u2588                                   \u2588\r\n  \u2588\u2588\u2581\u2581\u2581\u2581\u2581\u2581\u2581\u2581\u2581\u2581\u2581\u2581\u2581\u2581\u2581\u2581\u2588\u2581\u2581\u2581\u2588\u2581\u2581\u2581\u2581\u2581\u2581\u2581\u2581\u2581\u2581\u2581\u2581\u2581\u2581\u2581\u2581\u2581\u2581\u2581\u2581\u2581\u2581\u2581\u2581\u2581\u2581\u2581\u2581\u2581\u2581\u2581\u2581\u2581\u2581\u2581\u2588 \u2581\r\n  14.2 ms         Histogram: frequency by time        14.4 ms <\r\n\r\n Memory estimate: 47.78 KiB, allocs estimate: 320.\r\n\r\n```\r\n\r\nThe counterpart using the new branch `julia --project=\"environments/one_sided_branch\" --check-bounds=no`\r\n```julia \r\njulia> using NESAPOceananigans\r\njulia> set_problem_size!(500, 500, 50)\r\n\r\njulia> trial1 = run_model_benchmark!(momentum_kernel_test, GPU();\r\n                                     use_benchmarktools = true\r\nBenchmarkTools.Trial: 5 samples with 1 evaluation.\r\n Range (min \u2026 max):  16.463 ms \u2026  18.503 ms  \u250a GC (min \u2026 max): 0.00% \u2026 0.00%\r\n Time  (median):     16.466 ms               \u250a GC (median):    0.00%\r\n Time  (mean \u00b1 \u03c3):   16.878 ms \u00b1 908.449 \u03bcs  \u250a GC (mean \u00b1 \u03c3):  0.00% \u00b1 0.00%\r\n\r\n  \u2588\r\n  \u2588\u2581\u2581\u2581\u2581\u2581\u2581\u2581\u2581\u2581\u2581\u2581\u2581\u2581\u2581\u2581\u2581\u2581\u2581\u2581\u2581\u2581\u2581\u2581\u2581\u2581\u2581\u2581\u2581\u2581\u2581\u2581\u2581\u2581\u2581\u2581\u2581\u2581\u2581\u2581\u2581\u2581\u2581\u2581\u2581\u2581\u2581\u2581\u2581\u2581\u2581\u2581\u2581\u2581\u2581\u2581\u2581\u2581\u2581\u2586 \u2581\r\n  16.5 ms         Histogram: frequency by time         18.5 ms <\r\n\r\n Memory estimate: 250.06 KiB, allocs estimate: 676.\r\n\r\njulia> trial1 = run_model_benchmark!(tracer_kernel_test, arch;\r\n                                       use_benchmarktools = true)\r\nBenchmarkTools.Trial: 5 samples with 1 evaluation.\r\n Range (min \u2026 max):  6.695 ms \u2026   7.461 ms  \u250a GC (min \u2026 max): 0.00% \u2026 0.00%\r\n Time  (median):     6.789 ms               \u250a GC (median):    0.00%\r\n Time  (mean \u00b1 \u03c3):   6.908 ms \u00b1 312.944 \u03bcs  \u250a GC (mean \u00b1 \u03c3):  0.00% \u00b1 0.00%\r\n\r\n  \u2588     \u2588\u2588 \u2588                                                \u2588\r\n  \u2588\u2581\u2581\u2581\u2581\u2581\u2588\u2588\u2581\u2588\u2581\u2581\u2581\u2581\u2581\u2581\u2581\u2581\u2581\u2581\u2581\u2581\u2581\u2581\u2581\u2581\u2581\u2581\u2581\u2581\u2581\u2581\u2581\u2581\u2581\u2581\u2581\u2581\u2581\u2581\u2581\u2581\u2581\u2581\u2581\u2581\u2581\u2581\u2581\u2581\u2581\u2581\u2581\u2581\u2581\u2581\u2581\u2581\u2588 \u2581\r\n  6.69 ms         Histogram: frequency by time        7.46 ms <\r\n\r\n Memory estimate: 46.39 KiB, allocs estimate: 231.\r\n\r\n```\r\n\r\nP.S. some vestigial code not used is being removed as part of this PR because not beneficial (in terms of both accuracy and performance) that is\r\n- the JS weno formulation (dominated by the Z-weno formulation)\r\n- Velocity Upwinding for the vector invariant weno formulation (dominated by the other two formulations)",
    "changedFiles": 20,
    "closingIssuesReferences": [],
    "createdAt": "2024-07-22T17:50:41Z",
    "deletions": 1217,
    "labels": [],
    "mergedAt": "2024-07-25T00:46:07Z",
    "number": 3658,
    "title": "One-sided upwind reconstruction"
  }
]