[
  {
    "additions": 744,
    "author": {
      "id": "MDQ6VXNlcjE1MjcxOTQy",
      "is_bot": false,
      "login": "glwagner",
      "name": "Gregory L. Wagner"
    },
    "body": "This example resembles the case used in the Oceananiagns paper to showcase the various spherical grids that Oceananigans supports.\r\n\r\nCloses #2584",
    "changedFiles": 6,
    "closingIssuesReferences": [
      {
        "id": "I_kwDOCRy_aM5KnS-w",
        "number": 2584,
        "repository": {
          "id": "MDEwOlJlcG9zaXRvcnkxNTI4Nzg5NTI=",
          "name": "Oceananigans.jl",
          "owner": {
            "id": "MDEyOk9yZ2FuaXphdGlvbjQzMTYxMTg4",
            "login": "CliMA"
          }
        },
        "url": "https://github.com/CliMA/Oceananigans.jl/issues/2584"
      }
    ],
    "createdAt": "2025-12-26T17:38:48Z",
    "deletions": 5,
    "labels": [
      {
        "color": "d2b48c",
        "description": "The sacred scrolls",
        "id": "MDU6TGFiZWwxMjU1NjMxNjM1",
        "name": "documentation \ud83d\udcdc"
      },
      {
        "color": "b74b2d",
        "description": "",
        "id": "MDU6TGFiZWwxODc2ODk1ODMz",
        "name": "grids \ud83d\uddfa\ufe0f"
      }
    ],
    "mergedAt": "2025-12-30T05:29:16Z",
    "number": 5072,
    "title": "Add a spherical baroclinic instability example"
  },
  {
    "additions": 1,
    "author": {
      "id": "MDQ6VXNlcjcxMTI3Njg=",
      "is_bot": false,
      "login": "navidcy",
      "name": "Navid C. Constantinou"
    },
    "body": "",
    "changedFiles": 1,
    "closingIssuesReferences": [],
    "createdAt": "2025-12-30T05:34:59Z",
    "deletions": 1,
    "labels": [],
    "mergedAt": "2025-12-30T15:04:15Z",
    "number": 5088,
    "title": "Update citation format in comments"
  },
  {
    "additions": 1,
    "author": {
      "id": "MDQ6VXNlcjUwNjI0NTIx",
      "is_bot": false,
      "login": "xkykai",
      "name": "Xin Kai Lee"
    },
    "body": "fix function signature for target in the `Relaxation` docs",
    "changedFiles": 1,
    "closingIssuesReferences": [],
    "createdAt": "2025-12-30T14:18:57Z",
    "deletions": 1,
    "labels": [],
    "mergedAt": "2025-12-30T17:25:55Z",
    "number": 5089,
    "title": "fix error in docs for target function signature"
  },
  {
    "additions": 165,
    "author": {
      "id": "MDQ6VXNlcjE1MjcxOTQy",
      "is_bot": false,
      "login": "glwagner",
      "name": "Gregory L. Wagner"
    },
    "body": "Closes #1163\r\nCloses #5085\r\n\r\nI did this just for JLD2Writer, but we could also add this feature for NetCDFWriter if we want.",
    "changedFiles": 9,
    "closingIssuesReferences": [
      {
        "id": "MDU6SXNzdWU3Mzk1MDI4MTc=",
        "number": 1163,
        "repository": {
          "id": "MDEwOlJlcG9zaXRvcnkxNTI4Nzg5NTI=",
          "name": "Oceananigans.jl",
          "owner": {
            "id": "MDEyOk9yZ2FuaXphdGlvbjQzMTYxMTg4",
            "login": "CliMA"
          }
        },
        "url": "https://github.com/CliMA/Oceananigans.jl/issues/1163"
      },
      {
        "id": "I_kwDOCRy_aM7gdEnA",
        "number": 5085,
        "repository": {
          "id": "MDEwOlJlcG9zaXRvcnkxNTI4Nzg5NTI=",
          "name": "Oceananigans.jl",
          "owner": {
            "id": "MDEyOk9yZ2FuaXphdGlvbjQzMTYxMTg4",
            "login": "CliMA"
          }
        },
        "url": "https://github.com/CliMA/Oceananigans.jl/issues/5085"
      }
    ],
    "createdAt": "2025-12-27T21:49:50Z",
    "deletions": 100,
    "labels": [],
    "mergedAt": "2025-12-30T18:40:26Z",
    "number": 5080,
    "title": "Move initialization of JLD2Writer to run!"
  },
  {
    "additions": 90,
    "author": {
      "id": "MDQ6VXNlcjI2NjU3ODI4",
      "is_bot": false,
      "login": "jagoosw",
      "name": "Jago Strong-Wright"
    },
    "body": "Addresses #4916 \r\n\r\nHappy for others to edit but though I should start a draft for this.\r\n\r\n@glwagner @tomchor ",
    "changedFiles": 4,
    "closingIssuesReferences": [
      {
        "id": "I_kwDOCRy_aM7Wa1e4",
        "number": 4916,
        "repository": {
          "id": "MDEwOlJlcG9zaXRvcnkxNTI4Nzg5NTI=",
          "name": "Oceananigans.jl",
          "owner": {
            "id": "MDEyOk9yZ2FuaXphdGlvbjQzMTYxMTg4",
            "login": "CliMA"
          }
        },
        "url": "https://github.com/CliMA/Oceananigans.jl/issues/4916"
      }
    ],
    "createdAt": "2025-12-09T15:54:58Z",
    "deletions": 14,
    "labels": [
      {
        "color": "d2b48c",
        "description": "The sacred scrolls",
        "id": "MDU6TGFiZWwxMjU1NjMxNjM1",
        "name": "documentation \ud83d\udcdc"
      }
    ],
    "mergedAt": "2025-12-30T18:41:48Z",
    "number": 5026,
    "title": "Adds docs for perturbation advection"
  },
  {
    "additions": 151,
    "author": {
      "id": "MDQ6VXNlcjE1MjcxOTQy",
      "is_bot": false,
      "login": "glwagner",
      "name": "Gregory L. Wagner"
    },
    "body": "@jagoosw this PR refactors your original PR \"fix bam\". It addresses a few things:\r\n\r\n1. In the original implementation of BoundaryAdjacentMean, the flux average is taken over the whole domain, but only the boundary value is used. This PR makes it so that we perform the average over only the slice adjacent to the boundary, using `view`.\r\n2. I precompute and store the area for the flux.\r\n3. I removed the design wherein `BoundaryAdjacentMean` acts like a callable object. Instead, I extend `getbc` to extra the flux value. Also, I noticed that there is no need to store the flux within a Ref. It is fine to store the flux in a 1-element array, which is where the reduction ends up anyways.\r\n\r\nI also changed the name to `AverageBoundaryFlux` to emphasize the fact that this is a flux calculation.\r\n\r\nI'd also like to mention that on the original PR, I suggested using `Average`. But in the course of this work I realize this is not possible because boundary conditions must be available _before_ a field is constructed. Because of this chicken-egg issue, it is not possible to produce a boundary condition that depends on the average of a Field without a bit of contortion (which goes well beyond merely defining `regularize_field_boundary_conditions` --- it requires intercepting the `Field` constructor itself). For now, I decided it would be best to avoid extending / changing the `Field` constructor.\r\n\r\nIf you agree with these changes, I will merge this into your PR and continue there. Let me know!",
    "changedFiles": 2,
    "closingIssuesReferences": [],
    "createdAt": "2025-12-26T17:46:15Z",
    "deletions": 72,
    "labels": [
      {
        "color": "c3d657",
        "description": "",
        "id": "MDU6TGFiZWwxODkwNDMyNDEw",
        "name": "boundary conditions \ud83c\udfd3"
      }
    ],
    "mergedAt": "2025-12-30T18:44:27Z",
    "number": 5073,
    "title": "Refactor BoundaryAdjacentMean to AverageBoundaryFlux"
  },
  {
    "additions": 1119,
    "author": {
      "id": "MDQ6VXNlcjE1MjcxOTQy",
      "is_bot": false,
      "login": "glwagner",
      "name": "Gregory L. Wagner"
    },
    "body": "This PR implements a feature wherein FieldTimeSeries will automatically combine distributed data if it finds files called `filename_rank0`, `filename_rank1`, etc.\r\n\r\nA similar output combining was implemented by @taimoorsohail here: https://github.com/taimoorsohail/ocean-ensembles/blob/ts/parallel-run/analysis/combine2d_distributed.jl\r\n\r\nPart of this change also effectively requires `FieldTimeSeries` to work when only the prefix of a filename is provided, without the extension `.jld2`. So that is done as well.\r\n\r\nNon-combination can still be achieved by passing the specific filename, eg `FieldTimeSeries(filename_rank0, varname)` for the data on rank0.\r\n\r\nCloses #2351",
    "changedFiles": 7,
    "closingIssuesReferences": [
      {
        "id": "I_kwDOCRy_aM5Fmqmg",
        "number": 2351,
        "repository": {
          "id": "MDEwOlJlcG9zaXRvcnkxNTI4Nzg5NTI=",
          "name": "Oceananigans.jl",
          "owner": {
            "id": "MDEyOk9yZ2FuaXphdGlvbjQzMTYxMTg4",
            "login": "CliMA"
          }
        },
        "url": "https://github.com/CliMA/Oceananigans.jl/issues/2351"
      }
    ],
    "createdAt": "2025-12-27T21:28:24Z",
    "deletions": 6,
    "labels": [],
    "mergedAt": "2025-12-30T21:06:57Z",
    "number": 5079,
    "title": "Combine distributed data automagically in FieldTimeSeries"
  }
]