[
  {
    "additions": 41,
    "author": {
      "id": "MDQ6VXNlcjE4ODA2NDE=",
      "is_bot": false,
      "login": "charleskawczynski",
      "name": "Charles Kawczynski"
    },
    "body": "This PR unifies the Held Suarez dry and equil moist paper plots.",
    "changedFiles": 2,
    "closingIssuesReferences": [],
    "createdAt": "2022-12-08T21:37:32Z",
    "deletions": 194,
    "labels": [
      {
        "color": "428C04",
        "description": "",
        "id": "LA_kwDOFoZ0Vs7ibYPH",
        "name": "Refactor"
      },
      {
        "color": "A0A3D4",
        "description": "",
        "id": "LA_kwDOFoZ0Vs7iecG4",
        "name": "Visualization :art:"
      }
    ],
    "mergedAt": "2022-12-11T20:03:12Z",
    "number": 1192,
    "title": "Refactor HS paper plots"
  }
]