[
  {
    "additions": 6,
    "author": {
      "id": "MDQ6VXNlcjExNTk4NDMz",
      "is_bot": false,
      "login": "szy21",
      "name": "Zhaoyi Shen"
    },
    "body": "",
    "changedFiles": 1,
    "closingIssuesReferences": [],
    "createdAt": "2022-06-21T16:35:53Z",
    "deletions": 0,
    "labels": [],
    "mergedAt": "2022-06-21T17:15:21Z",
    "number": 549,
    "title": "Update pipeline.yml"
  },
  {
    "additions": 15,
    "author": {
      "id": "MDQ6VXNlcjQzNzEwMDQ1",
      "is_bot": false,
      "login": "akshaysridhar",
      "name": "Akshay Sridhar"
    },
    "body": "# PULL REQUEST\r\n\r\n## Purpose and Content\r\nAdd z_sfc to cache, access in surface flux computation. \r\n\r\n## Benefits and Risks\r\nAdds surface elevation for local dz computation (required in Surface Flux calculations). Local elevation can also be computed wherever necessary if the elevation profile function is known, but accessing via default cache seems more useful. Should not change behaviour of current tests in the absence of prescribed orography. \r\n\r\n## Linked Issues\r\n#408 \r\n\r\n## PR Checklist\r\n- [x] This PR has a corresponding issue OR is linked to an SDI.\r\n- [x] I have followed CliMA's codebase [contribution](https://clima.github.io/ClimateMachine.jl/latest/Contributing/) and [style](https://clima.github.io/ClimateMachine.jl/latest/DevDocs/CodeStyle/) guidelines OR N/A.\r\n- [x] I have followed CliMA's [documentation policy](https://github.com/CliMA/policies/wiki/Documentation-Policy).\r\n- [x] I have checked all issues and PRs and I certify that this PR does not duplicate an open PR.\r\n- [x] I linted my code on my local machine prior to submission OR N/A.\r\n- [N/A] Unit tests are included OR N/A. [Checked with buildkite regression tests]\r\n- [x] Code used in an integration test OR N/A.\r\n- [x] All tests ran successfully on my local machine OR N/A.\r\n- [x] All classes, modules, and function contain docstrings OR N/A.\r\n- [N/A] Documentation has been added/updated OR N/A.\r\n",
    "changedFiles": 2,
    "closingIssuesReferences": [],
    "createdAt": "2022-06-17T16:59:15Z",
    "deletions": 3,
    "labels": [],
    "mergedAt": "2022-06-21T17:54:20Z",
    "number": 543,
    "title": "Add surface elevation to default cache"
  }
]