[
  {
    "additions": 1,
    "author": {
      "id": "MDQ6VXNlcjE4ODA2NDE=",
      "is_bot": false,
      "login": "charleskawczynski",
      "name": "Charles Kawczynski"
    },
    "body": "This PR lowers the jet inference limit. I think the upgrade to Julia 1.9 fixed a bunch of these issues.",
    "changedFiles": 1,
    "closingIssuesReferences": [],
    "createdAt": "2023-09-07T00:16:27Z",
    "deletions": 1,
    "labels": [
      {
        "color": "d4c5f9",
        "description": "",
        "id": "LA_kwDOFoZ0Vs8AAAABScbh1A",
        "name": "Performance tests"
      }
    ],
    "mergedAt": "2023-09-07T01:11:12Z",
    "number": 2071,
    "title": "Lower jet inference limit"
  },
  {
    "additions": 18,
    "author": {
      "id": "MDQ6VXNlcjExOTY2OTY=",
      "is_bot": false,
      "login": "trontrytel",
      "name": "Anna Jaruga"
    },
    "body": "",
    "changedFiles": 6,
    "closingIssuesReferences": [
      {
        "id": "I_kwDOFoZ0Vs5vnkrX",
        "number": 2036,
        "repository": {
          "id": "MDEwOlJlcG9zaXRvcnkzNzc5MTAzNTg=",
          "name": "ClimaAtmos.jl",
          "owner": {
            "id": "MDEyOk9yZ2FuaXphdGlvbjQzMTYxMTg4",
            "login": "CliMA"
          }
        },
        "url": "https://github.com/CliMA/ClimaAtmos.jl/issues/2036"
      }
    ],
    "createdAt": "2023-09-03T18:06:46Z",
    "deletions": 14,
    "labels": [
      {
        "color": "18EC4D",
        "description": "",
        "id": "LA_kwDOFoZ0Vs79cmfg",
        "name": "ClimaParameters :control_knobs:"
      }
    ],
    "mergedAt": "2023-09-07T02:13:14Z",
    "number": 2053,
    "title": "trying to get rid of MSLP overwrite"
  },
  {
    "additions": 89,
    "author": {
      "id": "MDQ6VXNlcjQzNzEwMDQ1",
      "is_bot": false,
      "login": "akshaysridhar",
      "name": "Akshay Sridhar"
    },
    "body": "For each `longrun` buildkite label, this PR adds a `JOB_NAME` environment variable to the pipeline, which then assigns the yaml file,  data / output directories, figure directories, artifact paths. This replaces the current system where we have repeated references to the same verbose file / job name.  ",
    "changedFiles": 6,
    "closingIssuesReferences": [],
    "createdAt": "2023-09-06T21:57:59Z",
    "deletions": 63,
    "labels": [
      {
        "color": "89D76B",
        "description": "",
        "id": "LA_kwDOFoZ0Vs7wjPCy",
        "name": "House cleaning :broom:"
      }
    ],
    "mergedAt": "2023-09-07T18:26:15Z",
    "number": 2069,
    "title": "Adds env var for job name per buildkite step"
  },
  {
    "additions": 2,
    "author": {
      "id": "MDQ6VXNlcjkxNjc0ODU=",
      "is_bot": false,
      "login": "Sbozzolo",
      "name": "Gabriele Bozzola"
    },
    "body": "Julia in GitHub actions is still at version 1.8. \r\n",
    "changedFiles": 2,
    "closingIssuesReferences": [],
    "createdAt": "2023-09-07T17:30:39Z",
    "deletions": 2,
    "labels": [],
    "mergedAt": "2023-09-07T19:47:12Z",
    "number": 2075,
    "title": "Update GitHub Actions Julia to 1.9"
  },
  {
    "additions": 4,
    "author": {
      "id": "MDQ6VXNlcjkxNjc0ODU=",
      "is_bot": false,
      "login": "Sbozzolo",
      "name": "Gabriele Bozzola"
    },
    "body": "The documentation is generated with a few warnings and one error (see, e.g., https://github.com/CliMA/ClimaAtmos.jl/actions/runs/6101954504/job/16559376893#step:5:8).\r\n\r\nThe error is due to an incompatibility between `doctest` and `CitationBibliography`. I reported the problem upstream. The error is not fatal.",
    "changedFiles": 3,
    "closingIssuesReferences": [],
    "createdAt": "2023-09-06T20:53:00Z",
    "deletions": 16,
    "labels": [
      {
        "color": "0075ca",
        "description": "Improvements or additions to documentation",
        "id": "MDU6TGFiZWwzMDk1MzU0MjA1",
        "name": "documentation"
      },
      {
        "color": "89D76B",
        "description": "",
        "id": "LA_kwDOFoZ0Vs7wjPCy",
        "name": "House cleaning :broom:"
      }
    ],
    "mergedAt": "2023-09-07T20:46:16Z",
    "number": 2067,
    "title": "Clean up warnings in docs"
  }
]