[
  {
    "additions": 32,
    "author": {
      "id": "MDQ6VXNlcjE1MjcxOTQy",
      "is_bot": false,
      "login": "glwagner",
      "name": "Gregory L. Wagner"
    },
    "body": "This small PR encapsulates some of the functionality of `atmos_surface_conditions` so that it can be used elsewhere. It also tries to introduce a bit of notation hopefully to make the code a little clearer.\r\n\r\nWith @LenkaNovak and @akshaysridhar ",
    "changedFiles": 2,
    "closingIssuesReferences": [],
    "createdAt": "2024-03-28T23:17:11Z",
    "deletions": 17,
    "labels": [],
    "mergedAt": "2024-05-21T05:16:25Z",
    "number": 2855,
    "title": "Encapsulate surface conditions setting functionality so it can be reused"
  },
  {
    "additions": 19,
    "author": {
      "id": "MDQ6VXNlcjkxNjc0ODU=",
      "is_bot": false,
      "login": "Sbozzolo",
      "name": "Gabriele Bozzola"
    },
    "body": "Not quite like #1935, but almost functionally equivalent when you set the period to 1.\r\n\r\n(I cleaned up some unrelated config in the meantime)\r\n\r\nCloses #1935 \r\n",
    "changedFiles": 24,
    "closingIssuesReferences": [],
    "createdAt": "2024-05-20T17:26:22Z",
    "deletions": 24,
    "labels": [],
    "mergedAt": "2024-05-21T15:49:26Z",
    "number": 3032,
    "title": "Adds an option to periodically check for NaNs in the state"
  }
]