[
  {
    "additions": 1,
    "author": {
      "is_bot": true,
      "login": "app/github-actions"
    },
    "body": "This pull request changes the compat entry for the `SpecialFunctions` package from `1` to `1, 2`.\nThis keeps the compat entries for earlier versions.\n\n\n\nNote: I have not tested your package with this new compat entry.\nIt is your responsibility to make sure that your package tests pass before you merge this pull request.",
    "changedFiles": 1,
    "closingIssuesReferences": [],
    "createdAt": "2021-11-23T00:06:50Z",
    "deletions": 1,
    "labels": [],
    "mergedAt": "2021-11-23T01:15:40Z",
    "number": 50,
    "title": "CompatHelper: bump compat for SpecialFunctions to 2, (keep existing compat)"
  }
]