[
  {
    "additions": 1,
    "author": {
      "id": "MDQ6VXNlcjExOTY2OTY=",
      "is_bot": false,
      "login": "trontrytel",
      "name": "Anna Jaruga"
    },
    "body": "This bumps the `CloudMicrophysics.jl` version to allow merging P3 example in KID.\r\n\r\nI also deleted the `NEWS.md`. We weren't very good at updating it and whatever was there, was basically repeated automatically by Github when doing a release. Lets just make sure that our PR and commit descriptions are informative. I think this repo is small enough that we can get away with it.\r\n",
    "changedFiles": 2,
    "closingIssuesReferences": [],
    "createdAt": "2024-08-23T17:20:27Z",
    "deletions": 32,
    "labels": [],
    "mergedAt": "2024-08-23T17:41:10Z",
    "number": 447,
    "title": "Bump version for a new release, delete NEWS.md"
  }
]