[
  {
    "additions": 435,
    "author": {
      "id": "MDQ6VXNlcjIwNjk1NzQw",
      "is_bot": false,
      "login": "taimoorsohail",
      "name": "Taimoor Sohail"
    },
    "body": "This PR introduces a general restoring file that replaces `ECCORestoring` and associated functions with a general `Restoring` function that works with both ECCO and EN4. ",
    "changedFiles": 11,
    "closingIssuesReferences": [],
    "createdAt": "2025-04-23T00:55:25Z",
    "deletions": 451,
    "labels": [
      {
        "color": "a2eeef",
        "description": "New feature or request",
        "id": "LA_kwDOIOi2Ys8AAAABFpJxeQ",
        "name": "enhancement"
      },
      {
        "color": "370640",
        "description": "We must feed the models so they don't get cranky",
        "id": "LA_kwDOIOi2Ys8AAAABxYA3EA",
        "name": "data wrangling"
      },
      {
        "color": "0E8A16",
        "description": "clean up technical dept",
        "id": "LA_kwDOIOi2Ys8AAAAB7fyrIQ",
        "name": "cleanup \ud83e\uddf9"
      }
    ],
    "mergedAt": "2025-04-24T04:31:56Z",
    "number": 480,
    "title": "Generalize/Refactor ECCOrestoring \ud83d\udc49\ud83c\udffd DatasetRestoring to work with any dataset"
  },
  {
    "additions": 2,
    "author": {
      "id": "MDQ6VXNlcjMzNTQ3Njk3",
      "is_bot": false,
      "login": "simone-silvestri",
      "name": "Simone Silvestri"
    },
    "body": "it is called `sea_ice_concentration` and not `sea_ice_fraction`",
    "changedFiles": 2,
    "closingIssuesReferences": [],
    "createdAt": "2025-04-24T09:36:02Z",
    "deletions": 2,
    "labels": [],
    "mergedAt": "2025-04-24T12:41:18Z",
    "number": 483,
    "title": "Bugfix in default inpainting"
  },
  {
    "additions": 2,
    "author": {
      "id": "MDQ6VXNlcjMzNTQ3Njk3",
      "is_bot": false,
      "login": "simone-silvestri",
      "name": "Simone Silvestri"
    },
    "body": "I think this flux should be multipled by the concentration of the sea-ice in the cell?",
    "changedFiles": 1,
    "closingIssuesReferences": [],
    "createdAt": "2025-04-24T14:17:40Z",
    "deletions": 2,
    "labels": [],
    "mergedAt": "2025-04-24T16:51:06Z",
    "number": 484,
    "title": "Correct sea-ice ocean salt flux by concentration"
  }
]